{
  "project_info": {
    "project_number": "302408631726",
    "firebase_url": "https://analyticsandnotification.firebaseio.com",
    "project_id": "analyticsandnotification",
    "storage_bucket": "analyticsandnotification.appspot.com"
  },
  "client": [
    {
      "client_info": {
        "mobilesdk_app_id": "1:302408631726:android:68d925ee2cf455ff",
        "android_client_info": {
          "package_name": "com.example.arvindrathour.analyticsandnotification"
        }
      },
      "oauth_client": [
        {
          "client_id": "302408631726-6ht0drj3ajuosh6a1cb52es8jog22thv.apps.googleusercontent.com",
          "client_type": 1,
          "android_info": {
            "package_name": "com.example.arvindrathour.analyticsandnotification",
            "certificate_hash": "8493e708cee6cf2914c13ea73d6314c3c66f401d"
          }
        },
        {
          "client_id": "302408631726-peu6o5c4b3ku62u2h93tl7mhtdqka52u.apps.googleusercontent.com",
          "client_type": 1,
          "android_info": {
            "package_name": "com.example.arvindrathour.analyticsandnotification",
            "certificate_hash": "fe8448f5fd81d059a0633e88eccbbce7daa03ace"
          }
        },
        {
          "client_id": "302408631726-37j3ctg9ta116tf0fln9m5j47m82eu8v.apps.googleusercontent.com",
          "client_type": 3
        }
      ],
      "api_key": [
        {
          "current_key": "AIzaSyDUv3ygUN-LMX9hn1z9RmgCZTCn9np_qU8"
        }
      ],
      "services": {
        "analytics_service": {
          "status": 1
        },
        "appinvite_service": {
          "status": 2,
          "other_platform_oauth_client": [
            {
              "client_id": "302408631726-37j3ctg9ta116tf0fln9m5j47m82eu8v.apps.googleusercontent.com",
              "client_type": 3
            }
          ]
        },
        "ads_service": {
          "status": 2
        }
      }
    }
  ],
  "configuration_version": "1"
}